CHANGES.txt
CREDITS.txt
README.txt
bootstrap.py
buildout.cfg
setup.py
doc/Makefile
doc/conf.py
doc/index.txt
doc/make.bat
doc/overview.txt
serf/__init__.py
serf/conf.py
serf/core.py
serf/hash.py
serf/main.py
serf.egg-info/PKG-INFO
serf.egg-info/SOURCES.txt
serf.egg-info/dependency_links.txt
serf.egg-info/entry_points.txt
serf.egg-info/not-zip-safe
serf.egg-info/requires.txt
serf.egg-info/top_level.txt
serf/tests/__init__.py
serf/tests/tests.py
serf/tests/testdata1/index.html
serf/tests/testdata1/needs.html
serf/tests/testdata1/test.css
serf/tests/testdata1/test.foo
serf/tests/testdata1/test.html
serf/tests/testdata1/test.js
serf/tests/testdata1/test.json