Metadata-Version: 1.0
Name: serf
Version: 0.3.1
Summary: A web server to prototype rich client-side web apps
Home-page: UNKNOWN
Author: Martijn Faassen
Author-email: faassen@startifact.com
License: BSD
Keywords: wsgi javascript hurry.resource
Platform: UNKNOWN
Classifier: Development Status :: 4 - Beta
Classifier: Intended Audience :: Developers
Classifier: License :: OSI Approved :: BSD License
Classifier: Operating System :: OS Independent
Classifier: Programming Language :: Python
Classifier: Topic :: Internet :: WWW/HTTP :: Dynamic Content
Classifier: Topic :: Internet :: WWW/HTTP :: HTTP Servers
Classifier: Topic :: Internet :: WWW/HTTP :: WSGI :: Application
